gcp_adc_util/__init__.py
gcp_adc_util/inspect.py
gcp_adc_util-0.0.1.dist-info/LICENSE
gcp_adc_util-0.0.1.dist-info/METADATA
gcp_adc_util-0.0.1.dist-info/WHEEL
gcp_adc_util-0.0.1.dist-info/top_level.txt
gcp_adc_util-0.0.1.dist-info/RECORD
