Metadata-Version: 2.1
Name: gcp_adc_util
Version: 0.0.1
Summary: Utility library for GCP Application Default Credentials
Home-page: https://github.com/salrashid123/gcp_adc_util
Author: Sal Rashid
Author-email: salrashid123@gmail.com
Classifier: License :: OSI Approved :: Apache Software License
Classifier: Operating System :: OS Independent
Classifier: Development Status :: 3 - Alpha
Classifier: Intended Audience :: Developers
Classifier: Programming Language :: Python
Classifier: Programming Language :: Python :: 3.11
Classifier: Topic :: Software Development :: Libraries
Classifier: Topic :: Software Development :: Libraries :: Python Modules
License-File: LICENSE
Requires-Dist: google-auth>=2.36.0
Requires-Dist: requests
